appchen/__init__.py
appchen/eventing.py
appchen/server_send_events/__init__.py
appchen/server_send_events/client.py
appchen/server_send_events/routes.py
appchen/server_send_events/server.py
appchen/web_client/app-chen.d.ts
appchen/web_client/app.css
appchen/web_client/app.js
appchen/web_client/formen.js
appchen/web_client/io.js
appchen/web_client/message-discovery.js
appchen/web_client/time_interval.js
appchen/web_client/time_interval_component.js
appchen/web_client/codemirror/index.html
appchen/web_client/codemirror/addon/edit/closebrackets.js
appchen/web_client/codemirror/addon/edit/closetag.js
appchen/web_client/codemirror/addon/edit/continuelist.js
appchen/web_client/codemirror/addon/edit/matchbrackets.js
appchen/web_client/codemirror/addon/edit/matchtags.js
appchen/web_client/codemirror/addon/edit/trailingspace.js
appchen/web_client/codemirror/lib/codemirror.css
appchen/web_client/codemirror/lib/codemirror.js
appchen/web_client/codemirror/mode/javascript/javascript.js
appchen/web_demo/__init__.py
appchen/web_demo/app.css
appchen/web_demo/client.py
appchen/web_demo/live-trades.js
appchen/web_demo/myapp.html
appchen/web_demo/myapp.js
appchen/web_demo/run_server.py
appchen/web_demo/weblet1.js
appchen/web_demo/weblet3.js
appchen/weblet/__init__.py
appchen/weblet/editor.html
appchen-0.3.6.dist-info/METADATA
appchen-0.3.6.dist-info/WHEEL
appchen-0.3.6.dist-info/top_level.txt
appchen-0.3.6.dist-info/RECORD
