Metadata-Version: 2.1
Name: appchen
Version: 0.3.6
Summary: A client/server web framework based on Python and modern JavaScript.
Home-page: https://github.com/decatur/appchen
Author: Wolfgang Kühn
License: UNKNOWN
Platform: UNKNOWN
Requires-Python: >=3.6,<4.0
Requires-Dist: flask (<2.0,>=1.1)
Requires-Dist: gridchen (<0.2.0,>=0.1.3)
Requires-Dist: pymongo (<4.0,>=3.7)
Requires-Dist: requests (<3.0.0,>=2.18.0)
Requires-Dist: sseclient (<0.0.25,>=0.0.24)
